[
  {
    "id": "d6969b0e-8df3-4566-83ce-f2ddff26b99f",
    "data": [
      {
        "text": "hold ",
        "userDefined": false
      },
      {
        "text": "on",
        "meta": "@sys.ignore",
        "userDefined": false
      }
    ],
    "isTemplate": false,
    "count": 0,
    "lang": "en-gb",
    "updated": 0
  },
  {
    "id": "22f0b05c-90cb-4c1f-afca-a6a744791876",
    "data": [
      {
        "text": "could you wait",
        "userDefined": false
      }
    ],
    "isTemplate": false,
    "count": 0,
    "lang": "en-gb",
    "updated": 0
  },
  {
    "id": "a79aea41-134f-4882-a303-73559990ac14",
    "data": [
      {
        "text": "don",
        "meta": "@sys.ignore",
        "userDefined": false
      },
      {
        "text": "\u0027t ",
        "userDefined": false
      },
      {
        "text": "rush",
        "meta": "@sys.ignore",
        "userDefined": false
      }
    ],
    "isTemplate": false,
    "count": 0,
    "lang": "en-gb",
    "updated": 0
  },
  {
    "id": "47212d18-65d2-4bbc-ba55-5da2dd326d6e",
    "data": [
      {
        "text": "oh wait",
        "userDefined": false
      }
    ],
    "isTemplate": false,
    "count": 0,
    "lang": "en-gb",
    "updated": 0
  },
  {
    "id": "c64b264d-5bc9-48c7-91e4-16d8a7ab07ea",
    "data": [
      {
        "text": "wait a second",
        "userDefined": false
      }
    ],
    "isTemplate": false,
    "count": 0,
    "lang": "en-gb",
    "updated": 0
  },
  {
    "id": "42ba60bf-ccec-462a-b99d-4c5fc4e7effd",
    "data": [
      {
        "text": "wait please",
        "userDefined": false
      }
    ],
    "isTemplate": false,
    "count": 0,
    "lang": "en-gb",
    "updated": 0
  },
  {
    "id": "f05a1987-0004-4c81-887f-5e42b06546e7",
    "data": [
      {
        "text": "wait hold ",
        "userDefined": false
      },
      {
        "text": "on",
        "meta": "@sys.ignore",
        "userDefined": false
      }
    ],
    "isTemplate": false,
    "count": 0,
    "lang": "en-gb",
    "updated": 0
  },
  {
    "id": "e094d530-d157-4bf7-b1bc-b9a3a542306b",
    "data": [
      {
        "text": "wait",
        "userDefined": false
      }
    ],
    "isTemplate": false,
    "count": 0,
    "lang": "en-gb",
    "updated": 0
  }
]