[
  {
    "id": "3941f889-00ad-4780-8e0e-10444acc3ef4",
    "data": [
      {
        "text": "hug you",
        "userDefined": false
      }
    ],
    "isTemplate": false,
    "count": 0,
    "lang": "en-ca",
    "updated": 0
  },
  {
    "id": "a78bbda4-b696-4f53-b806-507df19f8c06",
    "data": [
      {
        "text": "do you want a hug",
        "userDefined": false
      }
    ],
    "isTemplate": false,
    "count": 0,
    "lang": "en-ca",
    "updated": 0
  },
  {
    "id": "c8248238-5237-4b09-9ac3-e1a137cb548c",
    "data": [
      {
        "text": "hug",
        "userDefined": false
      }
    ],
    "isTemplate": false,
    "count": 0,
    "lang": "en-ca",
    "updated": 0
  },
  {
    "id": "c5fb0434-c1a5-41ad-8e30-a23709fbcd95",
    "data": [
      {
        "text": "may I hug you",
        "userDefined": false
      }
    ],
    "isTemplate": false,
    "count": 1,
    "lang": "en-ca",
    "updated": 0
  },
  {
    "id": "61bb7bb1-2d4f-48a2-a2ac-abf93cbe31f3",
    "data": [
      {
        "text": "could you give ",
        "userDefined": false
      },
      {
        "text": "me",
        "meta": "@sys.ignore",
        "userDefined": false
      },
      {
        "text": " a hug",
        "userDefined": false
      }
    ],
    "isTemplate": false,
    "count": 0,
    "lang": "en-ca",
    "updated": 0
  },
  {
    "id": "183a9c92-1b78-48c7-9b93-3686631432ca",
    "data": [
      {
        "text": "you hugged",
        "userDefined": false
      }
    ],
    "isTemplate": false,
    "count": 0,
    "lang": "en-ca",
    "updated": 0
  },
  {
    "id": "f89d266a-eaa0-4f78-905a-77a6bcd59589",
    "data": [
      {
        "text": "hugged",
        "userDefined": false
      }
    ],
    "isTemplate": false,
    "count": 1,
    "lang": "en-ca",
    "updated": 0
  },
  {
    "id": "310a4927-8d2f-4d9f-a492-017f4fe0f958",
    "data": [
      {
        "text": "wanna hug",
        "userDefined": false
      }
    ],
    "isTemplate": false,
    "count": 1,
    "lang": "en-ca",
    "updated": 0
  },
  {
    "id": "2f08456b-170a-4d17-ac14-f1f240675ca4",
    "data": [
      {
        "text": "hug me",
        "userDefined": false
      }
    ],
    "isTemplate": false,
    "count": 1,
    "lang": "en-ca",
    "updated": 0
  },
  {
    "id": "1982f19c-08cf-4f8b-9795-04022b63f9bc",
    "data": [
      {
        "text": "hugging",
        "userDefined": false
      }
    ],
    "isTemplate": false,
    "count": 0,
    "lang": "en-ca",
    "updated": 0
  },
  {
    "id": "d1c84181-0e30-49f5-9f16-dcde6f5f545c",
    "data": [
      {
        "text": "a hug",
        "userDefined": false
      }
    ],
    "isTemplate": false,
    "count": 0,
    "lang": "en-ca",
    "updated": 0
  },
  {
    "id": "2f721546-0a19-4a05-92f1-88f6997e3e33",
    "data": [
      {
        "text": "want a hug",
        "userDefined": false
      }
    ],
    "isTemplate": false,
    "count": 1,
    "lang": "en-ca",
    "updated": 0
  },
  {
    "id": "f5bb12bd-49ff-414e-8376-071c0dea127a",
    "data": [
      {
        "text": "hugging me",
        "userDefined": false
      }
    ],
    "isTemplate": false,
    "count": 0,
    "lang": "en-ca",
    "updated": 0
  },
  {
    "id": "41c0c653-ab01-4bdf-bff3-08e1fefd4f1e",
    "data": [
      {
        "text": "I want a hug",
        "userDefined": false
      }
    ],
    "isTemplate": false,
    "count": 0,
    "lang": "en-ca",
    "updated": 0
  },
  {
    "id": "b98f0c36-8e91-4176-a15d-fd9768e94ef1",
    "data": [
      {
        "text": "hugged me",
        "userDefined": false
      }
    ],
    "isTemplate": false,
    "count": 1,
    "lang": "en-ca",
    "updated": 0
  }
]