[
  {
    "id": "07b0ac34-e565-4448-9798-af44a9ed67cb",
    "data": [
      {
        "text": "welcome",
        "meta": "@sys.ignore",
        "userDefined": false
      },
      {
        "text": " ",
        "userDefined": false
      },
      {
        "text": "here",
        "meta": "@sys.ignore",
        "userDefined": false
      }
    ],
    "isTemplate": false,
    "count": 0,
    "lang": "en",
    "updated": 0
  },
  {
    "id": "9fc2f6b9-0abe-44f0-a1c7-48049f5f36c4",
    "data": [
      {
        "text": "anytime",
        "userDefined": false
      }
    ],
    "isTemplate": false,
    "count": 0,
    "lang": "en",
    "updated": 0
  },
  {
    "id": "de7bd0e7-9c07-4781-851a-ac6906546862",
    "data": [
      {
        "text": "sure",
        "meta": "@sys.ignore",
        "userDefined": false
      },
      {
        "text": " ",
        "userDefined": false
      },
      {
        "text": "welcome",
        "meta": "@sys.ignore",
        "userDefined": false
      }
    ],
    "isTemplate": false,
    "count": 0,
    "lang": "en",
    "updated": 0
  },
  {
    "id": "c30a65cd-096c-4047-88f2-30fb2f4230b0",
    "data": [
      {
        "text": "you\u0027re so ",
        "userDefined": false
      },
      {
        "text": "welcome",
        "meta": "@sys.ignore",
        "userDefined": false
      }
    ],
    "isTemplate": false,
    "count": 0,
    "lang": "en",
    "updated": 0
  },
  {
    "id": "0f8dcc23-d363-4082-8b54-10f109d7fe36",
    "data": [
      {
        "text": "anything you want",
        "userDefined": false
      }
    ],
    "isTemplate": false,
    "count": 0,
    "lang": "en",
    "updated": 0
  },
  {
    "id": "0a361789-e6b4-4778-8048-86c55c8b05a4",
    "data": [
      {
        "text": "that\u0027s my pleasure",
        "userDefined": false
      }
    ],
    "isTemplate": false,
    "count": 0,
    "lang": "en",
    "updated": 0
  },
  {
    "id": "875e7d8d-e3ed-4e94-9e6c-e99a46dba419",
    "data": [
      {
        "text": "welcome",
        "meta": "@sys.ignore",
        "userDefined": false
      }
    ],
    "isTemplate": false,
    "count": 0,
    "lang": "en",
    "updated": 0
  },
  {
    "id": "d7dd1877-455b-45a2-a377-af46462dfd88",
    "data": [
      {
        "text": "my pleasure",
        "userDefined": false
      }
    ],
    "isTemplate": false,
    "count": 0,
    "lang": "en",
    "updated": 0
  },
  {
    "id": "319471c1-e12b-47ed-a4a3-03a5d70f114c",
    "data": [
      {
        "text": "you\u0027re ",
        "userDefined": false
      },
      {
        "text": "welcome",
        "meta": "@sys.ignore",
        "userDefined": false
      }
    ],
    "isTemplate": false,
    "count": 0,
    "lang": "en",
    "updated": 0
  }
]